infer_ci/__init__.py
infer_ci/__version__.py
infer_ci/auc.py
infer_ci/binary_metrics.py
infer_ci/classification_report.py
infer_ci/delong.py
infer_ci/evaluator.py
infer_ci/methods.py
infer_ci/object_detection_metrics.py
infer_ci/regression_metrics.py
infer_ci/takahashi_methods.py
infer_ci/utils.py
infer_ci/visualize.py
infer_ci-0.2.1.dist-info/licenses/LICENSE.txt
infer_ci-0.2.1.dist-info/METADATA
infer_ci-0.2.1.dist-info/WHEEL
infer_ci-0.2.1.dist-info/top_level.txt
infer_ci-0.2.1.dist-info/RECORD
