Metadata-Version: 2.4
Name: infer-ci
Version: 0.2.1
Summary: Model evaluation and confidence interval validation
Author-email: HumbleBeeAI <services@humblebee.ai>
Project-URL: Homepage, https://github.com/humblebeeai/infer-ci
Project-URL: Documentation, https://infer.humblebee.ai
Project-URL: Repository, https://github.com/humblebeeai/infer-ci.git
Project-URL: Issues, https://github.com/humblebeeai/infer-ci/issues
Project-URL: Changelog, https://github.com/humblebeeai/infer-ci/blob/main/CHANGELOG.md
Keywords: infer-ci,template,module,python,package
Classifier: Development Status :: 4 - Beta
Classifier: Intended Audience :: Developers
Classifier: Topic :: Software Development :: Libraries
Classifier: Operating System :: OS Independent
Classifier: Programming Language :: Python :: 3
Classifier: Programming Language :: Python :: 3.10
Classifier: Programming Language :: Python :: 3.11
Classifier: Programming Language :: Python :: 3.12
Classifier: Programming Language :: Python :: 3.13
Requires-Python: <4.0,>=3.10
License-File: LICENSE.txt
Requires-Dist: python-dotenv<2.0.0,>=1.0.1
Requires-Dist: pydantic[email,timezone]<3.0.0,>=2.0.3
Requires-Dist: pydantic-settings<3.0.0,>=2.2.1
Requires-Dist: statsmodels==0.14.5
Requires-Dist: scikit-learn==1.7.2
Requires-Dist: scipy==1.15.3
Requires-Dist: numpy==2.2.6
Requires-Dist: setuptools==68.2.2
Requires-Dist: pandas==2.3.3
Requires-Dist: pytest==8.4.2
Requires-Dist: matplotlib==3.10.6
Requires-Dist: seaborn==0.13.2
Requires-Dist: xgboost==3.0.5
Requires-Dist: tqdm==4.67.1
Requires-Dist: PyYAML==6.0.2
Provides-Extra: test
Requires-Dist: pytest<10.0.0,>=8.0.2; extra == "test"
Requires-Dist: pytest-cov<8.0.0,>=5.0.0; extra == "test"
Requires-Dist: pytest-xdist<4.0.0,>=3.6.1; extra == "test"
Requires-Dist: pytest-benchmark<6.0.0,>=5.0.1; extra == "test"
Provides-Extra: build
Requires-Dist: setuptools<81.0.0,>=70.3.0; extra == "build"
Requires-Dist: wheel<1.0.0,>=0.43.0; extra == "build"
Requires-Dist: build<2.0.0,>=1.1.1; extra == "build"
Requires-Dist: twine<7.0.0,>=6.0.1; extra == "build"
Provides-Extra: docs
Requires-Dist: pylint<4.0.0,>=3.0.4; extra == "docs"
Requires-Dist: mkdocs-material<10.0.0,>=9.5.50; extra == "docs"
Requires-Dist: mkdocs-awesome-nav<4.0.0,>=3.0.0; extra == "docs"
Requires-Dist: mkdocstrings[python]<1.0.0,>=0.24.3; extra == "docs"
Requires-Dist: mike<3.0.0,>=2.1.3; extra == "docs"
Provides-Extra: dev
Requires-Dist: pytest<10.0.0,>=8.0.2; extra == "dev"
Requires-Dist: pytest-cov<8.0.0,>=5.0.0; extra == "dev"
Requires-Dist: pytest-xdist<4.0.0,>=3.6.1; extra == "dev"
Requires-Dist: pytest-benchmark<6.0.0,>=5.0.1; extra == "dev"
Requires-Dist: setuptools<81.0.0,>=70.3.0; extra == "dev"
Requires-Dist: wheel<1.0.0,>=0.43.0; extra == "dev"
Requires-Dist: build<2.0.0,>=1.1.1; extra == "dev"
Requires-Dist: twine<7.0.0,>=6.0.1; extra == "dev"
Requires-Dist: pylint<4.0.0,>=3.0.4; extra == "dev"
Requires-Dist: mkdocs-material<10.0.0,>=9.5.50; extra == "dev"
Requires-Dist: mkdocs-awesome-nav<4.0.0,>=3.0.0; extra == "dev"
Requires-Dist: mkdocstrings[python]<1.0.0,>=0.24.3; extra == "dev"
Requires-Dist: mike<3.0.0,>=2.1.3; extra == "dev"
Requires-Dist: pyright<2.0.0,>=1.1.392; extra == "dev"
Requires-Dist: pre-commit<5.0.0,>=4.0.1; extra == "dev"
Dynamic: license-file
